setup.py
mprint/__init__.py
mprint/minput.py
mprint/mprint.py
mprint.egg-info/PKG-INFO
mprint.egg-info/SOURCES.txt
mprint.egg-info/dependency_links.txt
mprint.egg-info/not-zip-safe
mprint.egg-info/requires.txt
mprint.egg-info/top_level.txt