Metadata-Version: 1.1
Name: mprint
Version: 0.22
Summary: Use tags to print markup text on console screen
Home-page: http://www.github.com/h0m3/python-mprint
Author: Artur 'h0m3' Paiva
Author-email: dr.hoome@gmail.com
License: MIT
Keywords: print tags color markup
Platform: UNKNOWN
Classifier: Development Status :: 4 - Beta
Classifier: Intended Audience :: Developers
Classifier: License :: OSI Approved :: MIT License
Classifier: Natural Language :: English
Classifier: Operating System :: Microsoft
Classifier: Operating System :: POSIX
Classifier: Operating System :: Unix
Classifier: Programming Language :: Python :: 2.7
Classifier: Programming Language :: Python :: 3
Classifier: Topic :: Software Development :: User Interfaces
Classifier: Topic :: Terminals
